<?xml version="1.0" encoding="ISO-8859-1"?>
<EnvioDTE xmlns="http://www.sii.cl/SiiDte" xmlns:xsi="http://www.w3.org/2001/XMLSchema-instance" version="1.0" xsi:schemaLocation="http://www.sii.cl/SiiDte EnvioDTE_v10.xsd">
<SetDTE ID="EnvioDTE-92264000-9-76407152-2-20181224-043520-5F427ADA">
<Caratula version="1.0">
<RutEmisor>92264000-9</RutEmisor>
<RutEnvia>5544700-4</RutEnvia>
<RutReceptor>76407152-2</RutReceptor>
<FchResol>2014-08-22</FchResol>
<NroResol>80</NroResol>
<TmstFirmaEnv>2018-12-24T04:35:20</TmstFirmaEnv>
<SubTotDTE>
<TpoDTE>33</TpoDTE>
<NroDTE>1</NroDTE>
</SubTotDTE>
</Caratula>
<DTE xmlns="http://www.sii.cl/SiiDte" xmlns:xsi="http://www.w3.org/2001/XMLSchema-instance" version="1.0">
      <Documento ID="T33F1046790">
        <Encabezado>
          <IdDoc>
            <TipoDTE>33</TipoDTE>
            <Folio>1046790</Folio>
            <FchEmis>2018-12-21</FchEmis>
            <FmaPago>2</FmaPago>
            <FchVenc>2019-01-20</FchVenc>
          </IdDoc>
          <Emisor>
            <RUTEmisor>92264000-9</RUTEmisor>
            <RznSoc>Dynal Industrial S.A</RznSoc>
            <GiroEmis>INDUSTRIAL</GiroEmis>
            <Acteco>289990</Acteco>
            <DirOrigen>ESTACION CENTRAL</DirOrigen>
            <CmnaOrigen>SANTIAGO</CmnaOrigen>
            <CiudadOrigen>LORETO ARANDA ABARCA</CiudadOrigen>
          </Emisor>
          <Receptor>
            <RUTRecep>76407152-2</RUTRecep>
            <CdgIntRecep>76407152  </CdgIntRecep>
            <RznSocRecep>CONSTRUCTORA TECTON SPA</RznSocRecep>
            <GiroRecep>CONSTRUCCION</GiroRecep>
            <DirRecep>NUEVA DE LYON 0124, OF. 601</DirRecep>
            <CmnaRecep>PROVIDENCIA</CmnaRecep>
            <CiudadRecep>SANTIAGO            </CiudadRecep>
          </Receptor>
          <Totales>
            <MntNeto>457750</MntNeto>
            <TasaIVA>19</TasaIVA>
            <IVA>86973</IVA>
            <MntTotal>544723</MntTotal>
          </Totales>
        </Encabezado>
        <Detalle>
          <NroLinDet>1</NroLinDet>
          <CdgItem>
            <TpoCodigo>INT1</TpoCodigo>
            <VlrCodigo>450409168</VlrCodigo>
          </CdgItem>
          <NmbItem>FIELTRO LISO 15 L.B.S.</NmbItem>
          <QtyItem>15.000</QtyItem>
          <UnmdItem>UN</UnmdItem>
          <PrcItem>8650.00</PrcItem>
          <MontoItem>129750</MontoItem>
        </Detalle>
        <Detalle>
          <NroLinDet>2</NroLinDet>
          <CdgItem>
            <TpoCodigo>INT1</TpoCodigo>
            <VlrCodigo>450512016</VlrCodigo>
          </CdgItem>
          <NmbItem>MEMBRANA HIDROFUGA DYNEK ROLLO 75 MT2 (1,5X50)</NmbItem>
          <QtyItem>10.000</QtyItem>
          <UnmdItem>UN</UnmdItem>
          <PrcItem>32800.00</PrcItem>
          <MontoItem>328000</MontoItem>
        </Detalle>
        <Referencia>
          <NroLinRef>1</NroLinRef>
          <TpoDocRef>50</TpoDocRef>
          <FolioRef>1144119</FolioRef>
          <FchRef>2018-12-20</FchRef>
          <RazonRef></RazonRef>
        </Referencia>
        <Referencia>
          <NroLinRef>2</NroLinRef>
          <TpoDocRef>801</TpoDocRef>
          <FolioRef>04236</FolioRef>
          <FchRef>2018-12-18</FchRef>
          <RazonRef></RazonRef>
        </Referencia>
        <TED version="1.0">
          <DD>
            <RE>92264000-9</RE>
            <TD>33</TD>
            <F>1046790</F>
            <FE>2018-12-21</FE>
            <RR>76407152-2</RR>
            <RSR>CONSTRUCTORA TECTON SPA</RSR>
            <MNT>544723</MNT>
            <IT1>FIELTRO LISO 15 L.B.S.</IT1>
            <CAF version="1.0">
              <DA>
                <RE>92264000-9</RE>
                <RS>DYNAL INDUSTRIAL S A</RS>
                <TD>33</TD>
                <RNG>
                  <D>1016837</D>
                  <H>1052836</H>
                </RNG>
                <FA>2018-01-31</FA>
                <RSAPK>
                  <M>q2GEcWzfD5r8El3j3ZyYc0WVS3aHg+wEaxra70fi0D4xfKHlRuzItLBHMztOYMuRklppWtadiV6CNEnCxndTeQ==</M>
                  <E>Aw==</E>
                </RSAPK>
                <IDK>300</IDK>
              </DA>
              <FRMA algoritmo="SHA1withRSA">NEgFKtZ2tq0mvM8WKJ0+rtrVGQBKCbB/6tn7qgc7lo8fABpHf5ydjBLmV91zHvziRZyG+qp6C8gtqjNSQj1ljg==</FRMA>
            </CAF>
            <TSTED>2018-12-21T11:58:52</TSTED>
          </DD>
          <FRMT algoritmo="SHA1withRSA">R6EvTy1RUSF4QX75DqKjO1c76c0OoMr46F4YdAMFqNC/XM6mwRunEdAiJpXf6CJuA2iSTkI7K3WI
co3GCv6VEQ==</FRMT>
        </TED>
        <TmstFirma>2018-12-21T11:58:52</TmstFirma>
      </Documento>
      <Signature xmlns="http://www.w3.org/2000/09/xmldsig#">
	<SignedInfo>
		<CanonicalizationMethod Algorithm="http://www.w3.org/TR/2001/REC-xml-c14n-20010315"></CanonicalizationMethod>
		<SignatureMethod Algorithm="http://www.w3.org/2000/09/xmldsig#rsa-sha1"></SignatureMethod>
		<Reference URI="#T33F1046790">
			<DigestMethod Algorithm="http://www.w3.org/2000/09/xmldsig#sha1"></DigestMethod>
			<DigestValue>/bZ18eV4JXa91hr22tOtDt0xLvw=</DigestValue>
		</Reference>
	</SignedInfo>
	<SignatureValue>uZn3dj8vCKaaWOcWSA5yBM34hb59tVNYH6v3IAsBIrZN/y1DQLyNPgUgA5HXrwZ5oyg6ilgHwxw1
aGJjDCXKEmA5cCZ6mNSpTeQL7AvHuEoVWFfV8CcFs1mK6QFZAiYVCDkNgVZuXoZqzXAeAKyfy7rt
+CMeza83rywYOZ8R5Ys0iPip4QqETTPQT1s9HNwogocJh36LueMNFglTD9FS676EJynWT11GverD
azYl76ELcWpfAcLsvW2y/KnH2IBuDnt7tw2BpKAdmHREhvvFtxpPxU2opZY8JeCVlsGK1vqNEQTv
PdUJShxX9acJsm2y/7E2uxMHa6YgF4U5JWtL3Q==</SignatureValue>
	<KeyInfo>
		<KeyValue>
			<RSAKeyValue>
				<Modulus>0iZFU7Gr0DzfWgZV3dLxQBDNoVtu8OT41A/t3PsTwvIWUnYq4tj/njEfl2jhlcYm8Esr+6LO3f2X
RBcp0JUJ15ID4Usx6B6j2ebYj1uoiMiQtoLpMuWk6zTz9l5rDDIlX8XOCIvFBBubuIMCuEV21ARg
8HQixwZux7P7EIKQz/ZPlhnNyszj0JRiR59NhgQgwi8pHr1fEEEALtUccOhPw7g1GW+ZMsJP8I91
fOuj+vQ+v+KKTB8k4a2lGl2ippqnaPLk7bLKEaUNuPTeyoN87IkZR31R4ug716749GcOu5hb3T1C
6xr6/yQ/kb2HQxD8fNjRjw8S4YQfrVrfN3tYiw==</Modulus>
				<Exponent>AQAB</Exponent>
			</RSAKeyValue>
		</KeyValue>
		<X509Data>
			<X509Certificate>MIIF6TCCBNGgAwIBAgIDAT1bMA0GCSqGSIb3DQEBCwUAMIGmMQswCQYDVQQGEwJDTDEYMBYGA1UE
ChMPQWNlcHRhLmNvbSBTLkEuMUgwRgYDVQQDEz9BY2VwdGEuY29tIEF1dG9yaWRhZCBDZXJ0aWZp
Y2Fkb3JhIENsYXNlIDIgUGVyc29uYSBOYXR1cmFsIC0gRzQxHjAcBgkqhkiG9w0BCQEWD2luZm9A
YWNlcHRhLmNvbTETMBEGA1UEBRMKOTY5MTkwNTAtODAeFw0xNzA5MDUxMzQwMTZaFw0yMDA5MDUx
MzQwMTZaMIGFMQswCQYDVQQGEwJDTDEYMBYGA1UEDBMPUEVSU09OQSBOQVRVUkFMMSUwIwYDVQQD
ExxUT01BUyBKT1NFIEJSRU5ORVIgR1JVTlBFVEVSMSEwHwYJKoZIhvcNAQkBFhJqbGltb25hZG9A
ZHluYWwuY2wxEjAQBgNVBAUTCTUwODc0MTktMjCCASIwDQYJKoZIhvcNAQEBBQADggEPADCCAQoC
ggEBANImRVOxq9A831oGVd3S8UAQzaFbbvDk+NQP7dz7E8LyFlJ2KuLY/54xH5do4ZXGJvBLK/ui
zt39l0QXKdCVCdeSA+FLMegeo9nm2I9bqIjIkLaC6TLlpOs08/ZeawwyJV/FzgiLxQQbm7iDArhF
dtQEYPB0IscGbsez+xCCkM/2T5YZzcrM49CUYkefTYYEIMIvKR69XxBBAC7VHHDoT8O4NRlvmTLC
T/CPdXzro/r0Pr/iikwfJOGtpRpdoqaap2jy5O2yyhGlDbj03sqDfOyJGUd9UeLoO9eu+PRnDruY
W909Qusa+v8kP5G9h0MQ/HzY0Y8PEuGEH61a3zd7WIsCAwEAAaOCAj0wggI5MB8GA1UdIwQYMBaA
FGWlqz4/yLZRbRF+X8MKB+ZDoAi2MB0GA1UdDgQWBBQArf2Wo5EiH1uJuBdJqWbJfNouyzALBgNV
HQ8EBAMCBPAwHQYDVR0lBBYwFAYIKwYBBQUHAwIGCCsGAQUFBwMEMBEGCWCGSAGG+EIBAQQEAwIF
oDB1BgNVHSAEbjBsMGoGCCsGAQQBtWsCMF4wMQYIKwYBBQUHAgEWJWh0dHBzOi8vYWNnNC5hY2Vw
dGEuY29tL0NQUy1BY2VwdGFjb20wKQYIKwYBBQUHAgIwHTAWFg9BY2VwdGEuY29tIFMuQS4wAwIB
CRoDVEJEMFoGA1UdEgRTMFGgGAYIKwYBBAHBAQKgDBYKOTY5MTkwNTAtOKAkBggrBgEFBQcIA6AY
MBYMCjk2OTE5MDUwLTgGCCsGAQQBwQECgQ9pbmZvQGFjZXB0YS5jb20wWwYDVR0RBFQwUqAXBggr
BgEEAcEBAaALFgk1MDg3NDE5LTKgIwYIKwYBBQUHCAOgFzAVDAk1MDg3NDE5LTIGCCsGAQQBwQEC
gRJqbGltb25hZG9AZHluYWwuY2wwRwYIKwYBBQUHAQEEOzA5MDcGCCsGAQUFBzABhitodHRwczov
L2FjZzQuYWNlcHRhLmNvbS9hY2c0L29jc3AvQ2xhc2UyLUc0MD8GA1UdHwQ4MDYwNKAyoDCGLmh0
dHBzOi8vYWNnNC5hY2VwdGEuY29tL2FjZzQvY3JsL0NsYXNlMi1HNC5jcmwwDQYJKoZIhvcNAQEL
BQADggEBAI6/a8T6PpM49KU2ad5e9dlwVz+xnbICiCaR2O7Gxr99cupQRDg6CpUVG4C0Ycs6ab/N
zQJSTLx4pts1uXNDBtX6F8Zaq2/HtFAx45viqQ+uSwlo+FJ5lGgQaNFtjTVaSG1XRatpb5dCP5Pu
5SMLqkhjk4LePldRn9yRSthbjSVRW0uclJ4rvhs0rlxlm6pwzmOOAfwfLgbnXl0/WmNpYgSV1Vcp
dUr+CPLqUQrmzw1nQvvPXFlSKxskVbpxQ8yUGpNZBL76pATE/Ybr8Eoh8zh/DPigt09zjCu/MsOW
eu2KExK0TIx5+3JfTvlwjwj1FUBhi3qpJChSvdmcyR2LzCQ=</X509Certificate>
		</X509Data>
	</KeyInfo>
</Signature>
    </DTE></SetDTE>
<Signature xmlns="http://www.w3.org/2000/09/xmldsig#"><SignedInfo><CanonicalizationMethod Algorithm="http://www.w3.org/TR/2001/REC-xml-c14n-20010315"></CanonicalizationMethod><SignatureMethod Algorithm="http://www.w3.org/2000/09/xmldsig#rsa-sha1"></SignatureMethod><Reference URI="#EnvioDTE-92264000-9-76407152-2-20181224-043520-5F427ADA"><DigestMethod Algorithm="http://www.w3.org/2000/09/xmldsig#sha1"></DigestMethod><DigestValue>t31gzOE4BwhzBCf9OFctjrCWToU=</DigestValue></Reference></SignedInfo><SignatureValue>cZ1tU5AC4bP+Ga34m312eAfYwCU6M9tYZUm4ROflXAtn5tgm1g/nujrpPdbkuBx+7yNHRRQThKdT
tQWv0o+ehjpPF2rllO8ogy5i1nsSVdSZn/cPr03NN0u8XfSwiCzI0SHGBeubYMHGBrgv3c1zKagW
3JJal+O+XVi2OrUevRJ7+GO0Ol7iiqyiAve5HlCsOV6+AeHBtkPoItARbuuY10kKrnaCDPXZ49w3
rVuz+aOXmwdIgC9yv8xNu3VPy5BTknz2ZzuX1srXRdCuZ7NGWgAjZLX+bUkbDCJObI0tDh6kLuBg
AlMYXHBIfSLMnLX7pkmgrsUu5h2+znV9ipnKcQ==</SignatureValue><KeyInfo><KeyValue><RSAKeyValue><Modulus>lFOmbrg9OkK2yG7URNP9kaVZQLRvqYF4llzwx5YsJJ9l7pmmkrQxzHNy3kGPdBtX2LIE6GdX11br
qdGjBIs39SaptmIM0AHvQ5pe/5n/kKUw/hJebUo94RiNTaaKhYw3XcEZ2PcOkZkYNPRYGdNWGzyj
/5dI5r6wi3JVZRGI2a1mgNFS96sG84nQstYz1PMts7MUuiEK+ibRnmgKAmBKAj2cbHKcqkn9BzEO
8O83dYX6EQRxSyE2KRONqw7misVop0gcnVIiQm/vOs74rcGZ2t848X6vaVgrYsU+cQYETf7OrArh
vUpFU+0Iv+br9fxXIR9bxnGFj+ZbaNgAPfaDZQ==</Modulus><Exponent>AQAB</Exponent></RSAKeyValue></KeyValue><X509Data><X509Certificate>MIIF7zCCBNegAwIBAgIBFDANBgkqhkiG9w0BAQsFADCBpjELMAkGA1UEBhMCQ0wxGDAWBgNVBAoT
D0FjZXB0YS5jb20gUy5BLjFIMEYGA1UEAxM/QWNlcHRhLmNvbSBBdXRvcmlkYWQgQ2VydGlmaWNh
ZG9yYSBDbGFzZSAyIFBlcnNvbmEgTmF0dXJhbCAtIEc0MR4wHAYJKoZIhvcNAQkBFg9pbmZvQGFj
ZXB0YS5jb20xEzARBgNVBAUTCjk2OTE5MDUwLTgwHhcNMTYxMDA3MTkxNzU4WhcNMTkxMDA3MTkx
NzU4WjCBhjELMAkGA1UEBhMCQ0wxGDAWBgNVBAwTD1BFUlNPTkEgTkFUVVJBTDEfMB0GA1UEAxMW
UEFCTE8gSVpRVUlFUkRPIFdBTEtFUjEoMCYGCSqGSIb3DQEJARYZcGFibG9penF1aWVyZG93QGdt
YWlsLmNvbTESMBAGA1UEBRMJNTU0NDcwMC00MIIBIjANBgkqhkiG9w0BAQEFAAOCAQ8AMIIBCgKC
AQEAlFOmbrg9OkK2yG7URNP9kaVZQLRvqYF4llzwx5YsJJ9l7pmmkrQxzHNy3kGPdBtX2LIE6GdX
11brqdGjBIs39SaptmIM0AHvQ5pe/5n/kKUw/hJebUo94RiNTaaKhYw3XcEZ2PcOkZkYNPRYGdNW
Gzyj/5dI5r6wi3JVZRGI2a1mgNFS96sG84nQstYz1PMts7MUuiEK+ibRnmgKAmBKAj2cbHKcqkn9
BzEO8O83dYX6EQRxSyE2KRONqw7misVop0gcnVIiQm/vOs74rcGZ2t848X6vaVgrYsU+cQYETf7O
rArhvUpFU+0Iv+br9fxXIR9bxnGFj+ZbaNgAPfaDZQIDAQABo4ICRDCCAkAwHwYDVR0jBBgwFoAU
ZaWrPj/ItlFtEX5fwwoH5kOgCLYwHQYDVR0OBBYEFKp8iBzLRiGHokqiR7ocmLIYH65iMAsGA1Ud
DwQEAwIE8DAdBgNVHSUEFjAUBggrBgEFBQcDAgYIKwYBBQUHAwQwEQYJYIZIAYb4QgEBBAQDAgWg
MHUGA1UdIARuMGwwagYIKwYBBAG1awIwXjAxBggrBgEFBQcCARYlaHR0cHM6Ly9hY2c0LmFjZXB0
YS5jb20vQ1BTLUFjZXB0YWNvbTApBggrBgEFBQcCAjAdMBYWD0FjZXB0YS5jb20gUy5BLjADAgEJ
GgNUQkQwWgYDVR0SBFMwUaAYBggrBgEEAcEBAqAMFgo5NjkxOTA1MC04oCQGCCsGAQUFBwgDoBgw
FgwKOTY5MTkwNTAtOAYIKwYBBAHBAQKBD2luZm9AYWNlcHRhLmNvbTBiBgNVHREEWzBZoBcGCCsG
AQQBwQEBoAsWCTU1NDQ3MDAtNKAjBggrBgEFBQcIA6AXMBUMCTU1NDQ3MDAtNAYIKwYBBAHBAQKB
GXBhYmxvaXpxdWllcmRvd0BnbWFpbC5jb20wRwYIKwYBBQUHAQEEOzA5MDcGCCsGAQUFBzABhito
dHRwczovL2FjZzQuYWNlcHRhLmNvbS9hY2c0L29jc3AvQ2xhc2UyLUc0MD8GA1UdHwQ4MDYwNKAy
oDCGLmh0dHBzOi8vYWNnNC5hY2VwdGEuY29tL2FjZzQvY3JsL0NsYXNlMi1HNC5jcmwwDQYJKoZI
hvcNAQELBQADggEBAL0/jTzpAMmxX7v5w/dFYyQmTZPxN7fxWxKyf0np751stBTHnUExiFv+wqIv
E3iE5Znr8tMoeWwpDz+V0hgKqQDUtZipGbN2XNW19yS6JgenoNbv6dUbVpJwuYJeYcjhtXoePo64
AoP5cqM/xtcyVkePs2Y/fpBvehXC0qwq1zpxQkMNt+p+3UJqVH12qsMKBUw038Q+t4YIPG18W74c
KObVaxGG5A/YyTWsGM2Nupmc10p/yXgAZLDptlWA4h7/HHFJT8wRvAdBzhXo1IRsDrfBZ4cI93ts
fH0PdMlRqFg1zc3e+hA66nqxtua75CK21+fwx6cMP+rm7kRfVWA6tf4=</X509Certificate></X509Data></KeyInfo></Signature></EnvioDTE>