<?xml version="1.0" encoding="ISO-8859-1"?>
<EnvioDTE version="1.0" xmlns="http://www.sii.cl/SiiDte" xmlns:xsi="http://www.w3.org/2001/XMLSchema-instance" xsi:schemaLocation="http://www.sii.cl/SiiDte EnvioDTE_v10.xsd">
  <SetDTE ID="ID96808700-2__1__33__1003700">
    <Caratula version="1.0">
      <RutEmisor>96808700-2</RutEmisor>
      <RutEnvia>14681596-0</RutEnvia>
      <RutReceptor>76407152-2</RutReceptor>
      <FchResol>2006-12-15</FchResol>
      <NroResol>166</NroResol>
      <TmstFirmaEnv>2019-02-08T13:14:05</TmstFirmaEnv>
      
    <SubTotDTE><TpoDTE>33</TpoDTE><NroDTE>1</NroDTE></SubTotDTE></Caratula>
    
  <DTE version="1.0">
      <Documento ID="F1003700T33">
        <Encabezado>
          <IdDoc>
            <TipoDTE>33</TipoDTE>
            <Folio>1003700</Folio>
            <FchEmis>2019-02-08</FchEmis>
            <FmaPago>1</FmaPago>
            <MedioPago>EF</MedioPago>
            <FchVenc>2019-02-08</FchVenc>
          </IdDoc>
          <Emisor>
            <RUTEmisor>96808700-2</RUTEmisor>
            <RznSoc>BERMAD FLUID SOLUTIONS</RznSoc>
            <GiroEmis>IMPORTACION, EXPORTACION, REPRESENTACION Y COMERCIALIZA</GiroEmis>
            <Acteco>519000</Acteco>
            <DirOrigen>CARRETERA SAN MARTIN 16.500 SITIO 31</DirOrigen>
            <CmnaOrigen>Colina</CmnaOrigen>
            <CiudadOrigen>COLINA</CiudadOrigen>
          </Emisor>
          <Receptor>
            <RUTRecep>76407152-2</RUTRecep>
            <CdgIntRecep>76407152</CdgIntRecep>
            <RznSocRecep>CONSTRUCTORA TECTON SPA</RznSocRecep>
            <GiroRecep>CONTRUCCION</GiroRecep>
            <Contacto>PEDRO DUSSAILLANT</Contacto>
            <DirRecep>NUEVA DE LYON 0124 OF 601</DirRecep>
            <CmnaRecep>Providencia</CmnaRecep>
            <CiudadRecep>SANTIAGO</CiudadRecep>
          </Receptor>
          <Transporte>
            <DirDest>NUEVA DE LYON 0124 OF 601 - Providencia - SANTIAGO</DirDest>
          </Transporte>
          <Totales>
            <MntNeto>480000</MntNeto>
            <MntExe>0</MntExe>
            <TasaIVA>19.00</TasaIVA>
            <IVA>91200</IVA>
            <MntTotal>571200</MntTotal>
            <MontoPeriodo>571200</MontoPeriodo>
            <SaldoAnterior>0</SaldoAnterior>
            <VlrPagar>571200</VlrPagar>
          </Totales>
        </Encabezado>
        <Detalle>
          <NroLinDet>1</NroLinDet>
          <NmbItem>MEDIDOR CAUDAL 50mm TURBO BAR-16</NmbItem>
          <QtyRef>100.000000</QtyRef>
          <QtyItem>1.000000</QtyItem>
          <UnmdItem>UN</UnmdItem>
          <PrcItem>143500.000000</PrcItem>
          <MontoItem>143500</MontoItem>
        </Detalle>
        <Detalle>
          <NroLinDet>2</NroLinDet>
          <NmbItem>MEDIDOR CAUDAL 150mm TURBO BAR-16</NmbItem>
          <QtyRef>100.000000</QtyRef>
          <QtyItem>1.000000</QtyItem>
          <UnmdItem>UN</UnmdItem>
          <PrcItem>336500.000000</PrcItem>
          <MontoItem>336500</MontoItem>
        </Detalle>
        <Referencia>
          <NroLinRef>1</NroLinRef>
          <TpoDocRef>52</TpoDocRef>
          <FolioRef>1001608</FolioRef>
          <FchRef>2019-02-07</FchRef>
          <RazonRef>Segun Guia No. 1001608</RazonRef>
        </Referencia>
        <Referencia>
          <NroLinRef>2</NroLinRef>
          <TpoDocRef>802</TpoDocRef>
          <FolioRef>OV15966</FolioRef>
          <FchRef>2019-02-06</FchRef>
          <RazonRef>OV15966</RazonRef>
        </Referencia>
        <Referencia>
          <NroLinRef>3</NroLinRef>
          <TpoDocRef>801</TpoDocRef>
          <FolioRef>04604</FolioRef>
          <FchRef>2019-02-06</FchRef>
          <RazonRef>04604</RazonRef>
        </Referencia>
        <TED version="1.0">
          <DD>
            <RE>96808700-2</RE>
            <TD>33</TD>
            <F>1003700</F>
            <FE>2019-02-08</FE>
            <RR>76407152-2</RR>
            <RSR>CONSTRUCTORA TECTON SPA</RSR>
            <MNT>571200</MNT>
            <IT1>MEDIDOR CAUDAL 50mm TURBO BAR-16</IT1>
            <CAF version="1.0">
              <DA>
                <RE>96808700-2</RE>
                <RS>BERMAD FLUID SOLUTIONS S.A.</RS>
                <TD>33</TD>
                <RNG>
                  <D>1003361</D>
                  <H>1004359</H>
                </RNG>
                <FA>2018-10-19</FA>
                <RSAPK>
                  <M>zV8mjUfeKzIBcGHJ1MARTIHVO799jRu+IDG/aDmiNJQZAFmv83kXsRivSul06DFvLfmbgbeo9yQhLFHq8XMj0Q==</M>
                  <E>Aw==</E>
                </RSAPK>
                <IDK>300</IDK>
              </DA>
              <FRMA algoritmo="SHA1withRSA">UJbaRsR0xTecZOgAWdMHq6iYou2KbVC20GqjC9HEvuCO0x9xngBq+0GSW3m7jf0NC0VBT1K3rKWwHgY/9bCtIA==</FRMA>
            </CAF>
            <TSTED>2019-02-08T15:08:54</TSTED>
          </DD>
          <FRMT algoritmo="SHA1withRSA">X3qw1/d9teH5jMhF+BYOPBQ0SlmlezZCRHcTT9c7VuRRwO9mQDyw+VsgWC7E2T/Xu8Hg42R/BKwEVfmpUt5GWA==</FRMT>
        </TED>
        <TmstFirma>2019-02-08T15:08:58</TmstFirma>
      </Documento><Signature xmlns="http://www.w3.org/2000/09/xmldsig#"><SignedInfo><CanonicalizationMethod Algorithm="http://www.w3.org/TR/2001/REC-xml-c14n-20010315" /><SignatureMethod Algorithm="http://www.w3.org/2000/09/xmldsig#rsa-sha1" /><Reference URI="#F1003700T33"><Transforms><Transform Algorithm="http://www.w3.org/TR/2001/REC-xml-c14n-20010315" /></Transforms><DigestMethod Algorithm="http://www.w3.org/2000/09/xmldsig#sha1" /><DigestValue>uAPKr0vlvUp1mSI31rVnBzb7+Sk=</DigestValue></Reference></SignedInfo><SignatureValue>
QOiy5HgRKCoI7DqrW0J55jE/bwaT6IeH7aXpP4X+9FESKXcYG6GAcyNzbHnsRDPc
JONx+puh1WfVFcDqbUZwkuINSsoxuAxomsrzDLyuI9jh5K5Q5rjjFo6ElLA7DAXH
b6YdTqazLy8erlXfAY8+7IwLqJ9Hl+GUmU6zvZXWZefsGhIXJMuNRwvDNOebqbYx
s/NymKy8KAlGKkvOvr+XmMIRHgL5BN6wTevbfrsXqs5tkWV9WwXYCYFQi60moOeB
Rzy/Rm/6AZ2VIWm1ORgHKa1qDgeb39XibsjU+SX1KMZX5m1QimIiygN0CBpxFfMb
ix3W/b3WKVID3t4zt9x1+g==
</SignatureValue><KeyInfo><KeyValue><RSAKeyValue><Modulus>
vosZzpC0SeDiKTS9VhO/wXoMz4hf/zJuIgqp0Ivu++dP3vczeGiQywtmHauSZ01o
yuz8wVyARRAd4LbthkwD+lYiUlKCSvd7Fz3u4XKe+Kk7cd8bIVVlGKPJRIF4aZhx
ri1ouYfbntLlNSuLdkQoFTxYACVtVIx1MU/OIFYMw2/ixXS1NVzt3Si8YTJky/1E
wbnT03ZgTeeKaZ1lZ5SNFHx8/dqoVjhUrdy1Zk4nWxH+JOZUEvvrdL77zyViKPHA
WFHZzCiQZ7UeMi55N49VQCy7WeAEHksOuF21d5qFzr9Vm3jGl5/uu7jJgTMj2GID
S4bc0yBGmNCj/6CsbzwsQw==
</Modulus><Exponent>AQAB</Exponent></RSAKeyValue></KeyValue><X509Data><X509Certificate>
MIIGbzCCBVegAwIBAgIDAsQKMA0GCSqGSIb3DQEBCwUAMIGmMQswCQYDVQQGEwJD
TDEYMBYGA1UEChMPQWNlcHRhLmNvbSBTLkEuMUgwRgYDVQQDEz9BY2VwdGEuY29t
IEF1dG9yaWRhZCBDZXJ0aWZpY2Fkb3JhIENsYXNlIDIgUGVyc29uYSBOYXR1cmFs
IC0gRzQxHjAcBgkqhkiG9w0BCQEWD2luZm9AYWNlcHRhLmNvbTETMBEGA1UEBRMK
OTY5MTkwNTAtODAeFw0xODEyMTMyMDE0NDZaFw0yMTEyMTMyMDE0NDZaMIGHMQsw
CQYDVQQGEwJDTDEYMBYGA1UEDBMPUEVSU09OQSBOQVRVUkFMMSUwIwYDVQQDExxK
VUFOIEZSQU5DSVNDTyBGVUVOVEVTIFJJRkZPMSIwIAYJKoZIhvcNAQkBFhNqZnVl
bnRlc0BhZnNjb3JwLmNsMRMwEQYDVQQFEwoxMDM4MTIxMC0wMIIBIjANBgkqhkiG
9w0BAQEFAAOCAQ8AMIIBCgKCAQEAvosZzpC0SeDiKTS9VhO/wXoMz4hf/zJuIgqp
0Ivu++dP3vczeGiQywtmHauSZ01oyuz8wVyARRAd4LbthkwD+lYiUlKCSvd7Fz3u
4XKe+Kk7cd8bIVVlGKPJRIF4aZhxri1ouYfbntLlNSuLdkQoFTxYACVtVIx1MU/O
IFYMw2/ixXS1NVzt3Si8YTJky/1EwbnT03ZgTeeKaZ1lZ5SNFHx8/dqoVjhUrdy1
Zk4nWxH+JOZUEvvrdL77zyViKPHAWFHZzCiQZ7UeMi55N49VQCy7WeAEHksOuF21
d5qFzr9Vm3jGl5/uu7jJgTMj2GIDS4bc0yBGmNCj/6CsbzwsQwIDAQABo4ICwTCC
Ar0wHwYDVR0jBBgwFoAUZaWrPj/ItlFtEX5fwwoH5kOgCLYwHQYDVR0OBBYEFCaB
rGu8HW/OkWAybYSQ2RDW+YhVMAsGA1UdDwQEAwIE8DAdBgNVHSUEFjAUBggrBgEF
BQcDAgYIKwYBBQUHAwQwEQYJYIZIAYb4QgEBBAQDAgWgMIH1BgNVHSAEge0wgeow
gecGCCsGAQQBtWsCMIHaMDEGCCsGAQUFBwIBFiVodHRwczovL2FjZzQuYWNlcHRh
LmNvbS9DUFMtQWNlcHRhY29tMIGkBggrBgEFBQcCAjCBlzAWFg9BY2VwdGEuY29t
IFMuQS4wAwIBCRp9RWwgdGl0dWxhciBoYSBzaWRvIHZhbGlkYWRvIGVuIGZvcm1h
IG9ubGluZSwgcXVlZGFuZG8gaGFiaWxpdGFkbyBlbCBDZXJ0aWZpY2FkbyBwYXJh
IHVzbyB0cmlidXRhcmlvLCBwYWdvcywgY29tZXJjaW8geSBvdHJvcy4wWgYDVR0S
BFMwUaAYBggrBgEEAcEBAqAMFgo5NjkxOTA1MC04oCQGCCsGAQUFBwgDoBgwFgwK
OTY5MTkwNTAtOAYIKwYBBAHBAQKBD2luZm9AYWNlcHRhLmNvbTBeBgNVHREEVzBV
oBgGCCsGAQQBwQEBoAwWCjEwMzgxMjEwLTCgJAYIKwYBBQUHCAOgGDAWDAoxMDM4
MTIxMC0wBggrBgEEAcEBAoETamZ1ZW50ZXNAYWZzY29ycC5jbDBHBggrBgEFBQcB
AQQ7MDkwNwYIKwYBBQUHMAGGK2h0dHBzOi8vYWNnNC5hY2VwdGEuY29tL2FjZzQv
b2NzcC9DbGFzZTItRzQwPwYDVR0fBDgwNjA0oDKgMIYuaHR0cHM6Ly9hY2c0LmFj
ZXB0YS5jb20vYWNnNC9jcmwvQ2xhc2UyLUc0LmNybDANBgkqhkiG9w0BAQsFAAOC
AQEAT2LRVQAQBqgHSacMscY3ILXqBib5PII1kyzz7A3t7t3Kx5UGeLo7kBWOfpAK
S/DsTTOkmrPmaknko7Cm+qw2Lqxurb2O4jSSuHjykgEELdLmST4H+TuG8/h1UZXn
DcwbxzH9jDJgZ4RPIZe1MmXp8YV4KQmbSX/2CjyGisQDwuUfC7AuJQvEiMilJgTY
VDWzZMuwYrpLe3g0ENZl93ZmIDq41yTgzBVZ5e1J4x6PFp5Q/bRyfVpLKYYgOd2E
fS6QWF+8LAbn5ZekpiuXGD+o95XjGXCE9ymOt5kW4uqN7gd0U+0HricIhX1sY7Aa
S7fF7UOIdLsrg+hHKtjGTzbHSg==
</X509Certificate></X509Data></KeyInfo></Signature>
    </DTE></SetDTE><Signature xmlns="http://www.w3.org/2000/09/xmldsig#"><SignedInfo><CanonicalizationMethod Algorithm="http://www.w3.org/TR/2001/REC-xml-c14n-20010315" /><SignatureMethod Algorithm="http://www.w3.org/2000/09/xmldsig#rsa-sha1" /><Reference URI="#ID96808700-2__1__33__1003700"><Transforms><Transform Algorithm="http://www.w3.org/TR/2001/REC-xml-c14n-20010315" /></Transforms><DigestMethod Algorithm="http://www.w3.org/2000/09/xmldsig#sha1" /><DigestValue>9i1ccRANQZqNUtgi/MjK9A+t4kE=</DigestValue></Reference></SignedInfo><SignatureValue>
aZibe139IYBIDenFyFEBvu+cHw5eh8Mx9AaLXSA69+OCVMPS8lujmbey7xDApxIN
GzOWnUAd4XpZFqNFdgL2vzmonX3RH97vZoNfwlFoZVmBqW7ONECZnoz+AP+Xrt+2
9fDCsnTEcNfKnZ2JWCZckWV32DMrlz6dtqZjgULtthc=
</SignatureValue><KeyInfo><KeyValue><RSAKeyValue><Modulus>
pNci5AbduPBP7Bc36DAaicMVoTXwPQ6b1vvHKXZ2iZH/qiq3+a0fe5SFPzF+Yerp
7u5n+gYwfzziTA4sQip2A5BXg3QAvY2Lt+nAaCOs0z3lHFPps7pPQ+7bp7AbSASo
napBUhfFqdMZ7P3e6IAfTXdCOe7abupbfPJaT+fOEXk=
</Modulus><Exponent>AQAB</Exponent></RSAKeyValue></KeyValue><X509Data><X509Certificate>
MIIGbDCCBVSgAwIBAgIKdjB7JwAAAAuxQTANBgkqhkiG9w0BAQUFADCB0jELMAkG
A1UEBhMCQ0wxHTAbBgNVBAgTFFJlZ2lvbiBNZXRyb3BvbGl0YW5hMREwDwYDVQQH
EwhTYW50aWFnbzEUMBIGA1UEChMLRS1DRVJUQ0hJTEUxIDAeBgNVBAsTF0F1dG9y
aWRhZCBDZXJ0aWZpY2Fkb3JhMTAwLgYDVQQDEydFLUNFUlRDSElMRSBDQSBGSVJN
QSBFTEVDVFJPTklDQSBTSU1QTEUxJzAlBgkqhkiG9w0BCQEWGHNjbGllbnRlc0Bl
LWNlcnRjaGlsZS5jbDAeFw0xODA4MDIxMzUwMTdaFw0yMTA4MDExMzUwMTdaMIHt
MQswCQYDVQQGEwJDTDEiMCAGA1UECBMZTUVUUk9QT0xJVEFOQSBERSBTQU5USUFH
TzERMA8GA1UEBxMIU2FudGlhZ28xJjAkBgNVBAoTHVNvdXRoIENvbnN1bHRpbmcg
U2lnbmF0dXJlIFNBMSIwIAYDVQQLExlBdiBWaXRhY3VyYSAyNjcwIDZ0byBQaXNv
MScwJQYDVQQDEx5NYXJpbyBBdWd1c3RvIEZlcm5hbmRleiBDdWVzdGExMjAwBgkq
hkiG9w0BCQEWI21hcmlvLmZlcm5hbmRlekBzb3V0aGNvbnN1bHRpbmcuY29tMIGf
MA0GCSqGSIb3DQEBAQUAA4GNADCBiQKBgQCk1yLkBt248E/sFzfoMBqJwxWhNfA9
DpvW+8cpdnaJkf+qKrf5rR97lIU/MX5h6unu7mf6BjB/POJMDixCKnYDkFeDdAC9
jYu36cBoI6zTPeUcU+mzuk9D7tunsBtIBKidqkFSF8Wp0xns/d7ogB9Nd0I57tpu
6lt88lpP584ReQIDAQABo4ICqTCCAqUwggFPBgNVHSAEggFGMIIBQjCCAT4GCCsG
AQQBw1IFMIIBMDAtBggrBgEFBQcCARYhaHR0cDovL3d3dy5lLWNlcnRjaGlsZS5j
bC9DUFMuaHRtMIH+BggrBgEFBQcCAjCB8R6B7gBFAGwAIAByAGUAcwBwAG8AbgBk
AGUAcgAgAGUAcwB0AGUAIABmAG8AcgBtAHUAbABhAHIAaQBvACAAZQBzACAAdQBu
ACAAcgBlAHEAdQBpAHMAaQB0AG8AIABpAG4AZABpAHMAcABlAG4AcwBhAGIAbABl
ACAAcABhAHIAYQAgAGQAYQByACAAaQBuAGkAYwBpAG8AIABhAGwAIABwAHIAbwBj
AGUAcwBvACAAZABlACAAYwBlAHIAdABpAGYAaQBjAGEAYwBpAPMAbgAuACAAUABv
AHMAdABlAHIAaQBvAHIAbQBlAG4AdABlACwwHQYDVR0OBBYEFHzmg5mTx7ZZ4XrV
25jJ1jigC6GvMAsGA1UdDwQEAwIE8DAjBgNVHREEHDAaoBgGCCsGAQQBwQEBoAwW
CjE0NjgxNTk2LTAwHwYDVR0jBBgwFoAUeOE+n9ISs3o8jc0wDlOzQykHs1UwPgYD
VR0fBDcwNTAzoDGgL4YtaHR0cDovL2NybC5lLWNlcnRjaGlsZS5jbC9lY2VydGNo
aWxlY2FGRVMuY3JsMDoGCCsGAQUFBwEBBC4wLDAqBggrBgEFBQcwAYYeaHR0cDov
L29jc3AuZWNlcnRjaGlsZS5jbC9vY3NwMD0GCSsGAQQBgjcVBwQwMC4GJisGAQQB
gjcVCILcgy+Fk4xmhdWdF4Li3CeB7+w8YYHLnhSGqIJYAgFkAgEEMCMGA1UdEgQc
MBqgGAYIKwYBBAHBAQKgDBYKOTY5MjgxODAtNTANBgkqhkiG9w0BAQUFAAOCAQEA
S6x47s+jcHmHj/4B7lY2alo4J+txLZLkIslYJGDiDhTMgB+z7lD3txCHsK4UXBq8
wSqAho8UTfm8J3JFclFhxT2Fg/Loou8dp/sZhBW2wouYemp/z2EniyZPtSIw1oIn
+SI12mZJpjeJ0Tq9g3f54G0sYAh85fJ+M0DwlSW3MLpklSocZDVHlyZ/LA3DfgWt
bfFI5ZfAMIcpNVgIjZ7YXkkYiCm7mXL7dBj031ZvB4sSxTqXTQbxRB123+w0HFNz
9TMdX0PW5sKuiF6d1bJa+3CdiRHRqG/p6R+yFaEDeCQ58N7OX0BiMVxsnG15oOfE
XIcCBKy16v+gsuheQHs2gA==
</X509Certificate></X509Data></KeyInfo></Signature>
  
</EnvioDTE>